packaging_test_BensingIO/__init__.py
packaging_test_BensingIO/main.py
python_test_BensingIO-1.0.0.dist-info/LICENSE
python_test_BensingIO-1.0.0.dist-info/METADATA
python_test_BensingIO-1.0.0.dist-info/WHEEL
python_test_BensingIO-1.0.0.dist-info/top_level.txt
python_test_BensingIO-1.0.0.dist-info/RECORD
