Metadata-Version: 2.1
Name: python-test-BensingIO
Version: 1.0.0
Summary: The test package for structuring PyPi distributions
Author-email: Bill Bensing <bill@bensing.io>
Project-URL: Homepage, https://github.com/bensing-io/pypi-test-bensing-io
Classifier: Programming Language :: Python :: 3
Classifier: License :: OSI Approved :: Apache Software License
Classifier: Operating System :: OS Independent
Requires-Python: >=3.9
License-File: LICENSE
